async_progressbar.py
async_progressbar-0.1.2.dist-info/METADATA
async_progressbar-0.1.2.dist-info/WHEEL
async_progressbar-0.1.2.dist-info/licenses/LICENSE
async_progressbar-0.1.2.dist-info/RECORD
