Metadata-Version: 2.4
Name: async-progressbar
Version: 0.1.2
Summary: Add your description here
License-File: LICENSE
Requires-Python: >=3.9
Requires-Dist: ipywidgets>=8.1.7
